tinysort/__init__.py
tinysort/_backport_heapq.py
tinysort/_sort.py
tinysort/io.py
tinysort/tools.py
tinysort-0.1.dist-info/DESCRIPTION.rst
tinysort-0.1.dist-info/METADATA
tinysort-0.1.dist-info/RECORD
tinysort-0.1.dist-info/WHEEL
tinysort-0.1.dist-info/metadata.json
tinysort-0.1.dist-info/top_level.txt
tinysort-0.1.dist-info/zip-safe
