Metadata-Version: 2.0
Name: tinysort
Version: 0.1
Summary: Sort large amounts of Python objects that are larger than available memory but smaller than available disk.
Home-page: https://github.com/geowurster/tinysort
Author: Kevin Wurster
Author-email: wursterk@gmail.com
License: New BSD
Keywords: sorting tools memory
Platform: UNKNOWN
Classifier: Topic :: Utilities
Classifier: Intended Audience :: Developers
Classifier: Development Status :: 3 - Alpha
Classifier: License :: OSI Approved :: BSD License
Classifier: Topic :: Software Development :: Libraries
Classifier: Programming Language :: Python :: 2.7
Classifier: Programming Language :: Python :: 3.3
Classifier: Programming Language :: Python :: 3.4
Classifier: Programming Language :: Python :: 3.5
Classifier: Programming Language :: Python :: Implementation :: PyPy
Requires-Dist: six
Provides-Extra: dev
Requires-Dist: coveralls; extra == 'dev'
Requires-Dist: newlinejson; extra == 'dev'
Requires-Dist: pytest; extra == 'dev'
Requires-Dist: pytest-cov; extra == 'dev'
